quick_debug/__init__.py
quick_debug/quick_debug.py
quick_debug-0.0.3.dist-info/DESCRIPTION.rst
quick_debug-0.0.3.dist-info/METADATA
quick_debug-0.0.3.dist-info/RECORD
quick_debug-0.0.3.dist-info/WHEEL
quick_debug-0.0.3.dist-info/metadata.json
quick_debug-0.0.3.dist-info/top_level.txt
