Metadata-Version: 2.0
Name: quick-debug
Version: 0.0.3
Summary: Quick and simple debugging for Python scripts.
Home-page: https://github.com/nitred/quick_debug
Author: Nitish Reddy Koripalli
Author-email: nitish.k.reddy@gmail.com
License: MIT
Download-URL: https://github.com/nitred/quick_debug/master.tar.gz
Platform: UNKNOWN
Requires-Dist: future
Requires-Dist: requests
Requires-Dist: requests-futures
